tp3/verilog_vito/decode.v
module decode (
    input wire rst,
    input wire [0:3] cols,
    input wire [4:7] rows,
    output reg [0:3] key
);

// 8'b(cols)_(rows)
parameter [7:0] BTN_0 = 8'b0010_1000;       // col2 & row4
parameter [7:0] BTN_1 = 8'b0001_0001;       // col1 & row1  
parameter [7:0] BTN_2 = 8'b0010_0001;       // col2 & row1  
parameter [7:0] BTN_3 = 8'b0100_0001;       // col3 & row1  
parameter [7:0] BTN_4 = 8'b0001_0010;       // col1 & row2  
parameter [7:0] BTN_5 = 8'b0010_0010;       // col2 & row2  
parameter [7:0] BTN_6 = 8'b0100_0010;       // col3 & row2  
parameter [7:0] BTN_7 = 8'b0001_0100;       // col1 & row3
parameter [7:0] BTN_8 = 8'b0010_0100;       // col2 & row3
parameter [7:0] BTN_9 = 8'b0100_0100;       // col3 & row3
parameter [7:0] BTN_PLUS = 8'b1000_0001;    // col4 & row1 (TECLA A)
parameter [7:0] BTN_MINUS = 8'b1000_0010;   // col4 & row2 (TECLA B)
parameter [7:0] BTN_EQ = 8'b0100_0000;      // col4 & row3 (TECLA C)

// Decoding logic for button presses
always @(*) begin
    if (rst) begin
        key = 4'b0000; // Default value when reset
    end else begin
        case ({cols, rows}) 
            // First row (rows[0])
            BTN_1: key = 4'd1;  
            BTN_2: key = 4'd2;  
            BTN_3: key = 4'd3;  
            BTN_PLUS: key = 4'd10;  // hexa A

            // Second row (rows[1])
            BTN_4: key = 4'd4;  
            BTN_5: key = 4'd5;  
            BTN_6: key = 4'd6;  
            BTN_MINUS: key = 4'd11;  

            // Third row (rows[2])
            BTN_7: key = 4'd7;  
            BTN_8: key = 4'd8;  
            BTN_9: key = 4'd9;  
            BTN_EQ: key = 4'd12; 

            // Fourth row (rows[3])
            BTN_0: key = 4'd0;  
            default: key = 4'b0000;    
        endcase
    end
end

endmodule

tp3/src/keyboard_read.v
// modulo deteccion de teclado
module keyboard_read (
    input wire rst,
    //input wire enb,
    input wire clk_lf,          // clk de baja freq
    input wire clk_hf,          // clk de alta freq
    input wire [0:3] cols,      // entrada del teclado
    input wire [4:7] rows,      // "
    output reg button_pressed,  // actua como un enb para no leer mas numeros
    output reg is_op,         // si la tecla es una operacion
    output reg is_num,        // si la tecla es un numero
    output reg [0:1] which_op,        // que operacion se toco 
    // 1=suma 2=resta 3=igual 0=nada          
    output reg [0:3] which_num // que num se toco
);

reg [0:3]which_key; // registro que guarda la tecla que se toco
parameter [0:13]LF_CLK_FREQ = 14'd3; // low freq clk

// mecanica anti rebote:
// si se preisono una tecla
wire pressed;
assign pressed = rows[4] | rows[5] | rows [6] | rows[7];

reg [0:13]cnt; // 14 bits para contar hasta 10e3, o sea un segundo

// mantener la entrada en high una vez que se presiono una tecla 
// durante 10e3 ciclos de clock, o sea un segundo 
always @(posedge(clk_lf))
begin
    if (rst)
    begin
        cnt <= 14'd0;
        button_pressed <= 0;
    end
    else 
    begin
        if (pressed)
            button_pressed <= 1;
        if (button_pressed)
            cnt <= cnt + 14'd1;
        if ((cnt > LF_CLK_FREQ) && (!pressed))
        begin
            button_pressed <= 0;
            cnt <= 14'd0;
        end
        else if (cnt > LF_CLK_FREQ)
            cnt <= 14'd0;
    end
end
// esta es una senyal con flanco ascendente cuando se presiona una tecla
// y dura 10 ciclos de clock

// ahora decodifico con una LUT que tecla se presiono
wire [0:3]instant_key; // el valor de cols&rows en todo momento
decode decode1 (rst, cols, rows, instant_key);

// quiero quedarme con el valor de instant_key solo cuando se presiona una tecla y la clockeo con la lf_clk
reg [0:3]which_key_lf;
// se mantiene el valor de which_key hasta que se toque de nuevo otra tecla
always @(posedge(clk_lf))
begin
    if (rst) 
        which_key_lf <= 4'd0;
    else if (pressed) 
        which_key_lf <= instant_key;
end

// sincronizo con el clk de hf con dos DFF
reg [0:3]which_key_lf_sync1; // First stage synchronization flip-flop
reg [0:3]which_key_lf_sync2; // Second stage synchronization flip-flop
always @(posedge (clk_hf)) 
begin
    if (rst) 
    begin
        which_key <= 4'd0;
        which_key_lf_sync1 <= 4'd0;
        which_key_lf_sync2 <= 4'd0;
    end
    else 
    begin
        // Synchronize the low frequency signal into the high frequency clock domain
        which_key_lf_sync1 <= which_key_lf; // First flip-flop synchronizer
        which_key_lf_sync2 <= which_key_lf_sync1; // Second flip-flop synchronizer
        
        // Now assign the synchronized signal to which_key
        which_key <= which_key_lf_sync2;
    end
end

always @(posedge (clk_hf)) 
begin
    if(rst)
    begin
        is_op <= 0;
        is_num <= 0;
        which_op <= 2'd0;
        which_num <= 4'd0;
    end
    else
        if (which_key < 4'd10) // si es un numero
        begin
            is_op <= 0;
            is_num <= 1;
            which_op <= 2'd0; // nidea lo pongo en cero
            which_num <= which_key;
        end
        else // si es una operacion
        begin
            is_op <= 1;
            is_num <= 0;
            which_num <= 4'd0;
            case (which_key)
                4'hA: which_op = 2'd1; // es una suma
                4'hB: which_op = 2'd2; // es una resta
                4'hC: which_op = 2'd3; // es un igual
            endcase
        end
end

endmodule

tp3/verilog_vito/fsm_ringcounter4.v
//Implementacion de una maquina de estados de Moore en Verilog
module fsm_ringcounter4 (clk, reset, enable_in, out);
    input clk, reset, enable_in;   // Clock, reset, enable in
    output [3:0] out;          // Output
    //output [2:1] y;              // State output (para debug)

    reg [2:1] curr_y, next_Y;

    // Asignacion de estados
    parameter [2:1] E1 = 2'b00;
    parameter [2:1] E2 = 2'b01;
    parameter [2:1] E3 = 2'b10;
    parameter [2:1] E4 = 2'b11;

    // Logica de proximo estado (combinacional)
    always @(enable_in, curr_y)
        case (curr_y)
          E1:  if (enable_in == 1) 
					next_Y = E2;   
				 else 
					next_Y = E1; 
          
          E2:  if (enable_in == 1) 
					next_Y = E3;   
				 else 
					next_Y = E2; 
          
          E3:  if (enable_in == 1) 
					next_Y = E4;   
				 else 
					next_Y = E3; 
          
          E4:  if (enable_in == 1) 
					next_Y = E1;   
				 else 
					next_Y = E4; 

          
          default: next_Y = 2'bxx;
        endcase

    // Transicion al proximo estado (secuencial)
    always @(posedge reset, posedge clk)
        if (reset == 1) curr_y <= E1;
        else curr_y <= next_Y;

    // Salida (con assign)
    assign out[3] = (curr_y == E1);
    assign out[2] = (curr_y == E2);
    assign out[1] = (curr_y == E3);
    assign out[0] = (curr_y == E4);
endmodule

tp3/verilog_vito/keyboard_read_tb.v
`timescale 1ns/10ps

// Testbench for keyboard_read connected to fsm_ringcounter4
module keyboard_read_tb;

// Declare testbench signals
reg reset;
reg clk_lf; // low-frequency clock
reg clk_hf; // high-frequency clock
reg [3:0] rows;  // Rows for simulating key press
wire [3:0] cols; // Columns coming from fsm_ringcounter4
wire button_pressed;
wire is_op;
wire is_num;
wire [0:1] which_op;
wire [3:0] which_num; 

// Instantiate the fsm_ringcounter4 module
fsm_ringcounter4 ring_counter (
    .clk(clk_lf),  // Use low-frequency clock for the ring counter
    .reset(reset),
    .enable_in(1'b1), // Always enabled for the test
    .out(cols)  // Connect output to cols input of keyboard_read
);

// Instantiate the keyboard_read module
keyboard_read keyboard (
    .rst(reset),
    .clk_lf(clk_lf),
    .clk_hf(clk_hf),
    .cols(cols),
    .rows(rows),
    .button_pressed(button_pressed),
    .is_op(is_op),
    .is_num(is_num),
    .which_op(which_op),
    .which_num(which_num)
);

// Clock generation for both clk_lf (low-frequency) and clk_hf (high-frequency)
always begin
    #5 clk_lf = ~clk_lf; // Low-frequency clock (200 MHz)
end

always begin
    #1 clk_hf = ~clk_hf; // High-frequency clock (12 MHz)
end

// Test stimulus
initial begin
    // Initialize signals
    clk_lf = 0;
    clk_hf = 0;
    reset = 1;
    rows = 4'b0000;

    // Generate a VCD dump file for waveform visualization
    $dumpfile("keyboard_read_tb.vcd");
    $dumpvars(3);  // Set depth for signal tracing

    // Apply reset for a few clock cycles
    #10 reset = 0;  // Deassert reset after 10 ns

    // Simulate key press and release events for the rows

    // Simulate a press of key "1" (row 1)
    #10 rows = 4'b0001;  // Assert the first row (key press simulation)
    #6  rows = 4'b0000;  // Deassert rows to simulate key release
    #20 rows = 4'b0010;  // Assert second row
    #6  rows = 4'b0000;  // Deassert rows
    #30 rows = 4'b0100;  // Assert third row (another key press)
    #6  rows = 4'b0000;  // Deassert rows
    #50 rows = 4'b1000;  // Assert fourth row (yet another key press)
    #6  rows = 4'b0000;  // Deassert rows

    // Monitor the outputs
    // This part will help you track the values of the outputs during the simulation.
    #10;
    $display("At time %t:", $time);
    $display("button_pressed = %b, is_op = %b, is_num = %b, which_op = %b, which_num = %d",
             button_pressed, is_op, is_num, which_op, which_num);

    // Run the simulation for a few more cycles to observe behavior
    #200;

    // Finish the simulation
    $finish;
end

endmodule

tp3/verilog_vito/keyboard_read_tb.vcd
$date
	Fri Nov 29 13:37:35 2024
$end
$version
	Icarus Verilog
$end
$timescale
	10ps
$end
$scope module keyboard_read_tb $end
$var wire 2 ! which_op [0:1] $end
$var wire 4 " which_num [3:0] $end
$var wire 1 # is_op $end
$var wire 1 $ is_num $end
$var wire 4 % cols [3:0] $end
$var wire 1 & button_pressed $end
$var reg 1 ' clk_hf $end
$var reg 1 ( clk_lf $end
$var reg 1 ) reset $end
$var reg 4 * rows [3:0] $end
$scope module keyboard $end
$var wire 1 ' clk_hf $end
$var wire 1 ( clk_lf $end
$var wire 1 + pressed $end
$var wire 4 , rows [4:7] $end
$var wire 1 ) rst $end
$var wire 4 - instant_key [0:3] $end
$var wire 4 . cols [0:3] $end
$var parameter 14 / LF_CLK_FREQ $end
$var reg 1 & button_pressed $end
$var reg 14 0 cnt [0:13] $end
$var reg 1 $ is_num $end
$var reg 1 # is_op $end
$var reg 4 1 which_key [0:3] $end
$var reg 4 2 which_key_lf [0:3] $end
$var reg 4 3 which_key_lf_sync1 [0:3] $end
$var reg 4 4 which_key_lf_sync2 [0:3] $end
$var reg 4 5 which_num [0:3] $end
$var reg 2 6 which_op [0:1] $end
$scope module decode1 $end
$var wire 4 7 rows [4:7] $end
$var wire 1 ) rst $end
$var wire 4 8 cols [0:3] $end
$var parameter 8 9 BTN_0 $end
$var parameter 8 : BTN_1 $end
$var parameter 8 ; BTN_2 $end
$var parameter 8 < BTN_3 $end
$var parameter 8 = BTN_4 $end
$var parameter 8 > BTN_5 $end
$var parameter 8 ? BTN_6 $end
$var parameter 8 @ BTN_7 $end
$var parameter 8 A BTN_8 $end
$var parameter 8 B BTN_9 $end
$var parameter 8 C BTN_EQ $end
$var parameter 8 D BTN_MINUS $end
$var parameter 8 E BTN_PLUS $end
$var reg 4 F key [0:3] $end
$upscope $end
$upscope $end
$scope module ring_counter $end
$var wire 1 ( clk $end
$var wire 1 G enable_in $end
$var wire 1 ) reset $end
$var wire 4 H out [3:0] $end
$var parameter 2 I E1 $end
$var parameter 2 J E2 $end
$var parameter 2 K E3 $end
$var parameter 2 L E4 $end
$var reg 2 M curr_y [2:1] $end
$var reg 2 N next_Y [2:1] $end
$upscope $end
$upscope $end
$enddefinitions $end
$comment Show the parameter values. $end
$dumpall
b11 L
b10 K
b1 J
b0 I
b10000001 E
b10000010 D
b1000000 C
b1000100 B
b100100 A
b10100 @
b1000010 ?
b100010 >
b10010 =
b1000001 <
b100001 ;
b10001 :
b101000 9
b11 /
$end
#0
$dumpvars
b1 N
b0 M
b1000 H
1G
b0 F
b1000 8
b0 7
bx 6
bx 5
bx 4
bx 3
bx 2
bx 1
bx 0
b1000 .
b0 -
b0 ,
0+
b0 *
1)
0(
0'
x&
b1000 %
x$
x#
bx "
bx !
$end
#100
b0 4
b0 3
b0 1
b0 "
b0 5
b0 !
b0 6
0$
0#
1'
#200
0'
#300
1'
#400
0'
#500
0&
b0 0
b0 2
1'
1(
#600
0'
#700
1'
#800
0'
#900
1'
#1000
0'
0(
0)
#1100
1$
1'
#1200
0'
#1300
1'
#1400
0'
#1500
b10 N
b1100 -
b1100 F
b100 %
b100 .
b100 8
b100 H
b1 M
1'
1(
#1600
0'
#1700
1'
#1800
0'
#1900
1'
#2000
1+
b11 -
b11 F
0'
0(
b1 *
b1 ,
b1 7
#2100
1'
#2200
0'
#2300
1'
#2400
0'
#2500
b11 N
b10 -
b10 F
1&
b11 2
b10 %
b10 .
b10 8
b10 H
b10 M
1'
1(
#2600
0+
b0 -
b0 F
0'
b0 *
b0 ,
b0 7
#2700
b11 3
1'
#2800
0'
#2900
b11 4
1'
#3000
0'
0(
#3100
b11 1
1'
#3200
0'
#3300
b11 "
b11 5
1'
#3400
0'
#3500
b0 N
b1 0
b1 %
b1 .
b1 8
b1 H
b11 M
1'
1(
#3600
0'
#3700
1'
#3800
0'
#3900
1'
#4000
0'
0(
#4100
1'
#4200
0'
#4300
1'
#4400
0'
#4500
b1 N
b10 0
b1000 %
b1000 .
b1000 8
b1000 H
b0 M
1'
1(
#4600
1+
b1011 -
b1011 F
0'
b10 *
b10 ,
b10 7
#4700
1'
#4800
0'
#4900
1'
#5000
0'
0(
#5100
1'
#5200
0+
b0 -
b0 F
0'
b0 *
b0 ,
b0 7
#5300
1'
#5400
0'
#5500
b10 N
b1100 -
b1100 F
b11 0
b100 %
b100 .
b100 8
b100 H
b1 M
1'
1(
#5600
0'
#5700
1'
#5800
0'
#5900
1'
#6000
0'
0(
#6100
1'
#6200
0'
#6300
1'
#6400
0'
#6500
b11 N
b0 -
b0 F
b100 0
b10 %
b10 .
b10 8
b10 H
b10 M
1'
1(
#6600
0'
#6700
1'
#6800
0'
#6900
1'
#7000
0'
0(
#7100
1'
#7200
0'
#7300
1'
#7400
0'
#7500
b0 N
0&
b0 0
b1 %
b1 .
b1 8
b1 H
b11 M
1'
1(
#7600
0'
#7700
1'
#7800
0'
#7900
1'
#8000
0'
0(
#8100
1'
#8200
1+
b111 -
b111 F
0'
b100 *
b100 ,
b100 7
#8300
1'
#8400
0'
#8500
b1 N
b0 -
b0 F
1&
b111 2
b1000 %
b1000 .
b1000 8
b1000 H
b0 M
1'
1(
#8600
0'
#8700
b111 3
1'
#8800
0+
0'
b0 *
b0 ,
b0 7
#8900
b111 4
1'
#9000
0'
0(
#9100
b111 1
1'
#9200
0'
#9300
b111 "
b111 5
1'
#9400
0'
#9500
b10 N
b1100 -
b1100 F
b1 0
b100 %
b100 .
b100 8
b100 H
b1 M
1'
1(
#9600
0'
#9700
1'
#9800
0'
#9900
1'
#10000
0'
0(
#10100
1'
#10200
0'
#10300
1'
#10400
0'
#10500
b11 N
b0 -
b0 F
b10 0
b10 %
b10 .
b10 8
b10 H
b10 M
1'
1(
#10600
0'
#10700
1'
#10800
0'
#10900
1'
#11000
0'
0(
#11100
1'
#11200
0'
#11300
1'
#11400
0'
#11500
b0 N
b11 0
b1 %
b1 .
b1 8
b1 H
b11 M
1'
1(
#11600
0'
#11700
1'
#11800
0'
#11900
1'
#12000
0'
0(
#12100
1'
#12200
0'
#12300
1'
#12400
0'
#12500
b1 N
b100 0
b1000 %
b1000 .
b1000 8
b1000 H
b0 M
1'
1(
#12600
0'
#12700
1'
#12800
0'
#12900
1'
#13000
0'
0(
#13100
1'
#13200
0'
#13300
1'
#13400
0'
#13500
b10 N
b1100 -
b1100 F
0&
b0 0
b100 %
b100 .
b100 8
b100 H
b1 M
1'
1(
#13600
0'
#13700
1'
#13800
1+
b0 -
b0 F
0'
b1000 *
b1000 ,
b1000 7
#13900
1'
#14000
0'
0(
#14100
1'
#14200
0'
#14300
1'
#14400
0+
b1100 -
b1100 F
0'
b0 *
b0 ,
b0 7
#14500
b11 N
b0 -
b0 F
b10 %
b10 .
b10 8
b10 H
b10 M
1'
1(
#14600
0'
#14700
1'
#14800
0'
#14900
1'
#15000
0'
0(
#15100
1'
#15200
0'
#15300
1'
#15400
0'
#15500
b0 N
b1 %
b1 .
b1 8
b1 H
b11 M
1'
1(
#15600
0'
#15700
1'
#15800
0'
#15900
1'
#16000
0'
0(
#16100
1'
#16200
0'
#16300
1'
#16400
0'
#16500
b1 N
b1000 %
b1000 .
b1000 8
b1000 H
b0 M
1'
1(
#16600
0'
#16700
1'
#16800
0'
#16900
1'
#17000
0'
0(
#17100
1'
#17200
0'
#17300
1'
#17400
0'
#17500
b10 N
b1100 -
b1100 F
b100 %
b100 .
b100 8
b100 H
b1 M
1'
1(
#17600
0'
#17700
1'
#17800
0'
#17900
1'
#18000
0'
0(
#18100
1'
#18200
0'
#18300
1'
#18400
0'
#18500
b11 N
b0 -
b0 F
b10 %
b10 .
b10 8
b10 H
b10 M
1'
1(
#18600
0'
#18700
1'
#18800
0'
#18900
1'
#19000
0'
0(
#19100
1'
#19200
0'
#19300
1'
#19400
0'
#19500
b0 N
b1 %
b1 .
b1 8
b1 H
b11 M
1'
1(
#19600
0'
#19700
1'
#19800
0'
#19900
1'
#20000
0'
0(
#20100
1'
#20200
0'
#20300
1'
#20400
0'
#20500
b1 N
b1000 %
b1000 .
b1000 8
b1000 H
b0 M
1'
1(
#20600
0'
#20700
1'
#20800
0'
#20900
1'
#21000
0'
0(
#21100
1'
#21200
0'
#21300
1'
#21400
0'
#21500
b10 N
b1100 -
b1100 F
b100 %
b100 .
b100 8
b100 H
b1 M
1'
1(
#21600
0'
#21700
1'
#21800
0'
#21900
1'
#22000
0'
0(
#22100
1'
#22200
0'
#22300
1'
#22400
0'
#22500
b11 N
b0 -
b0 F
b10 %
b10 .
b10 8
b10 H
b10 M
1'
1(
#22600
0'
#22700
1'
#22800
0'
#22900
1'
#23000
0'
0(
#23100
1'
#23200
0'
#23300
1'
#23400
0'
#23500
b0 N
b1 %
b1 .
b1 8
b1 H
b11 M
1'
1(
#23600
0'
#23700
1'
#23800
0'
#23900
1'
#24000
0'
0(
#24100
1'
#24200
0'
#24300
1'
#24400
0'
#24500
b1 N
b1000 %
b1000 .
b1000 8
b1000 H
b0 M
1'
1(
#24600
0'
#24700
1'
#24800
0'
#24900
1'
#25000
0'
0(
#25100
1'
#25200
0'
#25300
1'
#25400
0'
#25500
b10 N
b1100 -
b1100 F
b100 %
b100 .
b100 8
b100 H
b1 M
1'
1(
#25600
0'
#25700
1'
#25800
0'
#25900
1'
#26000
0'
0(
#26100
1'
#26200
0'
#26300
1'
#26400
0'
#26500
b11 N
b0 -
b0 F
b10 %
b10 .
b10 8
b10 H
b10 M
1'
1(
#26600
0'
#26700
1'
#26800
0'
#26900
1'
#27000
0'
0(
#27100
1'
#27200
0'
#27300
1'
#27400
0'
#27500
b0 N
b1 %
b1 .
b1 8
b1 H
b11 M
1'
1(
#27600
0'
#27700
1'
#27800
0'
#27900
1'
#28000
0'
0(
#28100
1'
#28200
0'
#28300
1'
#28400
0'
#28500
b1 N
b1000 %
b1000 .
b1000 8
b1000 H
b0 M
1'
1(
#28600
0'
#28700
1'
#28800
0'
#28900
1'
#29000
0'
0(
#29100
1'
#29200
0'
#29300
1'
#29400
0'
#29500
b10 N
b1100 -
b1100 F
b100 %
b100 .
b100 8
b100 H
b1 M
1'
1(
#29600
0'
#29700
1'
#29800
0'
#29900
1'
#30000
0'
0(
#30100
1'
#30200
0'
#30300
1'
#30400
0'
#30500
b11 N
b0 -
b0 F
b10 %
b10 .
b10 8
b10 H
b10 M
1'
1(
#30600
0'
#30700
1'
#30800
0'
#30900
1'
#31000
0'
0(
#31100
1'
#31200
0'
#31300
1'
#31400
0'
#31500
b0 N
b1 %
b1 .
b1 8
b1 H
b11 M
1'
1(
#31600
0'
#31700
1'
#31800
0'
#31900
1'
#32000
0'
0(
#32100
1'
#32200
0'
#32300
1'
#32400
0'
#32500
b1 N
b1000 %
b1000 .
b1000 8
b1000 H
b0 M
1'
1(
#32600
0'
#32700
1'
#32800
0'
#32900
1'
#33000
0'
0(
#33100
1'
#33200
0'
#33300
1'
#33400
0'
#33500
b10 N
b1100 -
b1100 F
b100 %
b100 .
b100 8
b100 H
b1 M
1'
1(
#33600
0'
#33700
1'
#33800
0'
#33900
1'
#34000
0'
0(
#34100
1'
#34200
0'
#34300
1'
#34400
0'
#34500
b11 N
b0 -
b0 F
b10 %
b10 .
b10 8
b10 H
b10 M
1'
1(
